caseswitcher/__init__.py
caseswitcher/py.typed
case_switcher-1.3.4.dist-info/LICENSE
case_switcher-1.3.4.dist-info/WHEEL
case_switcher-1.3.4.dist-info/METADATA
case_switcher-1.3.4.dist-info/RECORD
