Metadata-Version: 2.1
Name: case-switcher
Version: 1.3.4
Summary: Library to change the casing of strings.
Home-page: https://gitlab.com/mburkard/case-switcher
License: MIT
Keywords: string,string manipulation,case convention,camel case,dot case,kebab case,pascal case,snake case,title case
Author: Matthew Burkard
Author-email: matthewjburkard@gmail.com
Requires-Python: >=3.9,<4.0
Classifier: License :: OSI Approved :: MIT License
Classifier: Programming Language :: Python :: 3
Classifier: Programming Language :: Python :: 3.10
Classifier: Programming Language :: Python :: 3.9
Project-URL: Repository, https://gitlab.com/mburkard/case-switcher
